{
	"class" : {
		"from:to:type:" : "gk 5/4/2006 11:18" },
	"instance" : {
		"=" : "kb 5/31/2007 22:51",
		"clone" : "gk 5/9/2006 12:44",
		"disconnect" : "kb 6/25/2007 19:05",
		"from" : "gk 5/4/2006 11:00",
		"from:" : "gk 5/4/2006 11:00",
		"from:to:type:" : "gk 5/4/2006 11:19",
		"hash" : "gk 5/9/2006 12:42",
		"isValid" : "gk 5/12/2006 14:07",
		"labelFrom:" : "gk 5/12/2006 13:32",
		"reconnectIn:" : "kb 6/25/2007 19:05",
		"renderFrom:on:in:" : "gk 6/26/2007 00:52",
		"renderObjectIn:on:" : "gk 5/8/2006 14:51",
		"to" : "gk 5/4/2006 11:00",
		"to:" : "gk 5/4/2006 11:00",
		"type" : "gk 5/4/2006 10:39",
		"type:" : "gk 5/4/2006 10:40" } }
