{
	"class" : {
		"checkExternalProgramPaths" : "miki 10/16/2008 12:58",
		"cleanImage" : "sig 01/23/2009 10:27",
		"initializePlatform" : "sig 01/23/2009 10:27",
		"launchFrom:" : "miki 12/4/2008 13:09",
		"openDoits" : "gk 11/17/2008 12:07",
		"openWelcome" : "gk 11/17/2008 12:09",
		"prepareDevImage" : "jupiter 09/04/2014 11:09",
		"recreateDemoDatabase:" : "gk 11/16/2007 11:26",
		"recreateMinimalDatabase" : "gk 11/1/2006 14:03",
		"recreateSimpleDatabase" : "miki 11/10/2008 15:58",
		"recreateTestDatabase" : "gk 11/16/2007 11:26",
		"recreateTortureDatabase" : "gk 11/16/2007 11:26",
		"release" : "jupiter 07/15/2014 04:13",
		"sanityCheck" : "miki 10/16/2008 12:58",
		"setDeveloperUIPreferencesFontSize:" : "miki 11/17/2008 09:35",
		"setRepositories" : "gk 11/22/2006 16:49",
		"startAsRemoteMagmaServer" : "miki 11/17/2008 14:47",
		"startOfflineClient" : "miki 11/18/2008 11:27",
		"startSeaside" : "miki 11/18/2008 11:32",
		"startServer" : "miki 11/18/2008 12:06",
		"startServerMockStatistics" : "rpb 6/25/2007 13:49",
		"startServerWithRemoteMagma" : "miki 11/18/2008 11:44",
		"startStatisticsTest" : "miki 11/18/2008 11:45",
		"stopSeaside" : "miki 12/4/2008 12:38",
		"stopServer" : "miki 12/4/2008 14:30",
		"stopStatisticsTest" : "miki 11/18/2008 11:45",
		"timeStarted" : "gk 9/6/2006 13:55",
		"timeStarted:" : "miki 11/18/2008 11:46",
		"ultraCleanImage" : "gk 10/5/2006 12:35",
		"useGemStone" : "jupiter 09/05/2014 12:54",
		"version" : "jupiter 07/19/2014 13:21" },
	"instance" : {
		"seeClassSide" : "gk 11/12/2008 14:31" } }
